eikonsai/__init__.py
eikonsai/context.py
eikonsai/jobs.py
eikonsai/models.py
eikonsai/similarity.py
eikonsai/utils.py
eikonsai-0.0.9.3.dist-info/METADATA
eikonsai-0.0.9.3.dist-info/WHEEL
eikonsai-0.0.9.3.dist-info/licenses/LICENCE.md
eikonsai-0.0.9.3.dist-info/RECORD
