Metadata-Version: 2.4
Name: eikonsai
Version: 0.0.9.3
Summary: A simple python SDK to connect with the Eikon geospatial platform.
Project-URL: Homepage, https://github.com/Kennedy821/eikon
Project-URL: Issues, https://github.com/Kennedy821/eikon
Author-email: Tariro Mashongamhende <sluggailtd@gmail.com>
License-File: LICENCE.md
Classifier: License :: OSI Approved :: GNU General Public License v3 (GPLv3)
Classifier: Operating System :: OS Independent
Classifier: Programming Language :: Python :: 3.9
Classifier: Programming Language :: Python :: 3.10
Classifier: Programming Language :: Python :: 3.11
Classifier: Programming Language :: Python :: 3.12
Requires-Python: >=3.9
Requires-Dist: numpy==2.0.2
Requires-Dist: pandas==2.2.3
Requires-Dist: pillow==10.4.0
Requires-Dist: requests==2.32.3
